LICENSE
MANIFEST.in
README.rst
pgparse.c
pgparse.pyx
setup.cfg
setup.py
libpg_query/LICENSE
libpg_query/Makefile
libpg_query/pg_query.h
libpg_query/src/pg_query.c
libpg_query/src/pg_query_deparse.c
libpg_query/src/pg_query_fingerprint.c
libpg_query/src/pg_query_fingerprint.h
libpg_query/src/pg_query_fingerprint_conds.c
libpg_query/src/pg_query_fingerprint_defs.c
libpg_query/src/pg_query_internal.h
libpg_query/src/pg_query_json_helper.c
libpg_query/src/pg_query_json_plpgsql.c
libpg_query/src/pg_query_json_plpgsql.h
libpg_query/src/pg_query_normalize.c
libpg_query/src/pg_query_outfuncs.h
libpg_query/src/pg_query_outfuncs_conds.c
libpg_query/src/pg_query_outfuncs_defs.c
libpg_query/src/pg_query_outfuncs_json.c
libpg_query/src/pg_query_outfuncs_protobuf.c
libpg_query/src/pg_query_parse.c
libpg_query/src/pg_query_parse_plpgsql.c
libpg_query/src/pg_query_readfuncs.h
libpg_query/src/pg_query_readfuncs_conds.c
libpg_query/src/pg_query_readfuncs_defs.c
libpg_query/src/pg_query_readfuncs_protobuf.c
libpg_query/src/pg_query_scan.c
libpg_query/src/pg_query_split.c
libpg_query/src/postgres/contrib_pgcrypto_sha1.c
libpg_query/src/postgres/guc-file.c
libpg_query/src/postgres/src_backend_catalog_namespace.c
libpg_query/src/postgres/src_backend_catalog_pg_proc.c
libpg_query/src/postgres/src_backend_commands_define.c
libpg_query/src/postgres/src_backend_libpq_pqcomm.c
libpg_query/src/postgres/src_backend_nodes_bitmapset.c
libpg_query/src/postgres/src_backend_nodes_copyfuncs.c
libpg_query/src/postgres/src_backend_nodes_equalfuncs.c
libpg_query/src/postgres/src_backend_nodes_extensible.c
libpg_query/src/postgres/src_backend_nodes_list.c
libpg_query/src/postgres/src_backend_nodes_makefuncs.c
libpg_query/src/postgres/src_backend_nodes_nodeFuncs.c
libpg_query/src/postgres/src_backend_nodes_value.c
libpg_query/src/postgres/src_backend_parser_gram.c
libpg_query/src/postgres/src_backend_parser_parse_expr.c
libpg_query/src/postgres/src_backend_parser_parser.c
pgparse.egg-info/PKG-INFO
pgparse.egg-info/SOURCES.txt
pgparse.egg-info/dependency_links.txt
pgparse.egg-info/top_level.txt
pgparse.egg-info/zip-safe